<Properties StartupConfiguration="{BB039D9A-E43E-1963-6E31-BD65F9E3185A}|">
  <MonoDevelop.Ide.Workbench ActiveDocument="Assets/Scripts/Racer.cs">
    <Files>
      <File FileName="Assets/Scripts/GameHandler.cs" Line="196" Column="1" />
      <File FileName="Assets/Scripts/Racer.cs" Line="109" Column="58" />
      <File FileName="Assets/Scripts/WordSubmitter.cs" />
      <File FileName="Assets/Scripts/Racer1.cs" Line="32" Column="1" />
      <File FileName="Assets/Scripts/Letter.cs" />
      <File FileName="Assets/Scripts/AIRacer.cs" />
      <File FileName="Assets/Scripts/Racer2.cs" />
      <File FileName="Assets/Scripts/Floor.cs" Line="116" Column="10" />
      <File FileName="Assets/Scripts/MainMenuText.cs" />
    </Files>
    <Pads>
      <Pad Id="ProjectPad">
        <State name="__root__">
          <Node name="TypeByke" expanded="True">
            <Node name="Assets" expanded="True">
              <Node name="Scripts" expanded="True">
                <Node name="Racer.cs" selected="True" />
              </Node>
            </Node>
          </Node>
        </State>
      </Pad>
    </Pads>
  </MonoDevelop.Ide.Workbench>
  <MonoDevelop.Ide.DebuggingService.PinnedWatches />
  <MonoDevelop.Ide.Workspace ActiveConfiguration="Debug" />
  <MonoDevelop.Ide.ItemProperties.Assembly-CSharp PreferredExecutionTarget="c9eb341e-be47-416d-958a-c0e7c6678fb1" />
  <MonoDevelop.Ide.DebuggingService.Breakpoints>
    <BreakpointStore />
  </MonoDevelop.Ide.DebuggingService.Breakpoints>
  <MultiItemStartupConfigurations />
</Properties>